port_forward_manager/__init__.py
port_forward_manager/cli.py
port_forward_manager/cli_group.py
port_forward_manager/cli_schema.py
port_forward_manager/cli_session.py
port_forward_manager/cli_ssh_group.py
port_forward_manager/core/__init__.py
port_forward_manager/core/autocomplete.py
port_forward_manager/core/database.py
port_forward_manager/core/forward_sessions.py
port_forward_manager/core/models.py
port_forward_manager/core/normalisation.py
port_forward_manager/core/tools.py
port_forward_manager/core/ui.py
port_forward_manager-4.0.7.dist-info/METADATA
port_forward_manager-4.0.7.dist-info/WHEEL
port_forward_manager-4.0.7.dist-info/entry_points.txt
port_forward_manager-4.0.7.dist-info/RECORD
