Metadata-Version: 2.3
Name: port-forward-manager
Version: 4.0.7
Summary: Port forwarding manager
Author: Vladimiro Casinha
Author-email: vcasinha@kjoo.net
Requires-Python: >=3.10,<4.0
Classifier: Programming Language :: Python :: 3
Classifier: Programming Language :: Python :: 3.10
Classifier: Programming Language :: Python :: 3.11
Classifier: Programming Language :: Python :: 3.12
Classifier: Programming Language :: Python :: 3.13
Requires-Dist: PyYAML (>=6.0,<7.0)
Requires-Dist: Pygments (>=2.13.0,<3.0.0)
Requires-Dist: click (>=8.1.3,<9.0.0)
Requires-Dist: colorama (>=0.4.6,<0.5.0)
Requires-Dist: commonmark (>=0.9.1,<0.10.0)
Requires-Dist: pydantic (>=2.9.1,<3.0.0)
Requires-Dist: rich (>=13.8.1,<14.0.0)
Requires-Dist: shellingham (>=1.5.0,<2.0.0)
Requires-Dist: simplejson (>=3.17.6,<4.0.0)
Requires-Dist: sqlalchemy (>=2.0.34,<3.0.0)
Requires-Dist: sqlmodel (>=0.0.22,<0.0.23)
Requires-Dist: sshconf (>=0.2.5,<0.3.0)
Requires-Dist: typer (>=0.12.5,<0.13.0)
Project-URL: Repository, https://github.com/kxiros/port-forward-manager
